mixer/__init__.py
mixer/_compat.py
mixer/_faker.py
mixer/auto.py
mixer/factory.py
mixer/main.py
mixer/markov.py
mixer/mix_types.py
mixer/backend/__init__.py
mixer/backend/django.py
mixer/backend/flask.py
mixer/backend/marshmallow.py
mixer/backend/mongoengine.py
mixer/backend/peewee.py
mixer/backend/pony.py
mixer/backend/sqlalchemy.py
mixer/resources/file.txt
mixer/resources/image.gif
mixer-7.2.2.dist-info/LICENSE
mixer-7.2.2.dist-info/METADATA
mixer-7.2.2.dist-info/WHEEL
mixer-7.2.2.dist-info/top_level.txt
mixer-7.2.2.dist-info/RECORD
